lockbox/__init__.py
lockbox/cli.py
lockbox/core.py
lockbox-0.1.dist-info/DESCRIPTION.rst
lockbox-0.1.dist-info/METADATA
lockbox-0.1.dist-info/RECORD
lockbox-0.1.dist-info/WHEEL
lockbox-0.1.dist-info/entry_points.txt
lockbox-0.1.dist-info/metadata.json
lockbox-0.1.dist-info/top_level.txt
