Metadata-Version: 2.0
Name: lockbox
Version: 0.1
Summary: User-friendly symmetric-key cryptography
Home-page: https://github.com/johnwheeler/lockbox
Author: John Wheeler
Author-email: john@johnwheeler.org
License: UNKNOWN
Platform: UNKNOWN
Classifier: Development Status :: 5 - Production/Stable
Classifier: Programming Language :: Python
Classifier: Programming Language :: Python :: 2
Classifier: Programming Language :: Python :: 2.6
Classifier: Programming Language :: Python :: 2.7
Classifier: Programming Language :: Python :: 3
Classifier: Programming Language :: Python :: 3.1
Classifier: Programming Language :: Python :: 3.2
Classifier: Programming Language :: Python :: 3.3
Classifier: Programming Language :: Python :: 3.4
Classifier: Programming Language :: Python :: 3.5
Classifier: Programming Language :: Python :: 3.6
Classifier: Environment :: Console
Classifier: Intended Audience :: Developers
Classifier: Intended Audience :: System Administrators
Classifier: License :: OSI Approved :: BSD License
Classifier: Topic :: Software Development
Classifier: Topic :: Terminals
Classifier: Topic :: Text Processing
Classifier: Topic :: Utilities
Requires-Dist: click (>=6.7)
Requires-Dist: cryptography (>=1.8.1)
